{
  "url": "https://vnexpress.net/quoc-gia-nao-co-bien-gioi-ngan-nhat-hanh-tinh-4964757.html",
  "title": "Quốc gia nào có biên giới ngắn nhất hành tinh?",
  "date": "Thứ hai, 17/11/2025, 19:00 (GMT+7)",
  "description": "Châu Âu là lục địa có nhiều quốc gia diện tích nhỏ nhất cũng như có đường biên ngắn nhất thế giới",
  "content": "Quốc gia nào có biên giới ngắn nhất hành tinh Châu Âu là lục địa có nhiều quốc gia diện tích nhỏ nhất cũng như có đường biên ngắn nhất thế giới Anh Minh Theo Guinness World Records World Atlas Britanica"
}